drkaizeng_linear_regression-0.0.1.dist-info/METADATA
drkaizeng_linear_regression-0.0.1.dist-info/WHEEL
drkaizeng_linear_regression-0.0.1.dist-info/entry_points.txt
linear_regression/__init__.py
linear_regression/__pycache__/__init__.cpython-314.pyc
linear_regression/__pycache__/linear_regression.cpython-314.pyc
linear_regression/linear_regression.py
linear_regression/linear_regression_python_bindings.cpython-314-x86_64-linux-gnu.so
drkaizeng_linear_regression-0.0.1.dist-info/RECORD
