Metadata-Version: 2.4
Name: drkaizeng-linear-regression
Version: 0.0.1
Classifier: Development Status :: 4 - Beta
Classifier: Intended Audience :: Developers
Classifier: Intended Audience :: Science/Research
Classifier: Topic :: Scientific/Engineering
Classifier: Topic :: Scientific/Engineering :: Mathematics
Classifier: Topic :: Software Development :: Libraries
Classifier: License :: OSI Approved :: MIT License
Classifier: Programming Language :: Python :: 3
Classifier: Programming Language :: Python :: 3 :: Only
Classifier: Programming Language :: Python :: 3.13
Classifier: Programming Language :: Rust
Classifier: Operating System :: OS Independent
Classifier: Environment :: Console
Requires-Dist: click>=8.3.1
Requires-Dist: numpy>=2.4.0
Summary: A Python wrapper around rust_projects/linear_regression.
Author: Kai Zeng
Requires-Python: >=3.13
Project-URL: Homepage, https://statistics-and-engineering-lab.readthedocs.io/en/latest/python_projects/linear_regression/
